figh-0.1.0.dist-info/METADATA
figh-0.1.0.dist-info/WHEEL
figh-0.1.0.dist-info/licenses/LICENSE
figh/__init__.py
figh/base.py
figh/config_file_format.py
figh/errors.py
figh/github.py
figh/util.py
figh-0.1.0.dist-info/RECORD
