Metadata-Version: 2.1
Name: figh
Version: 0.1.0
Summary: version controlled configuration storage
Author-Email: skspark <wondershine.one@gmail.com>
License: MIT
Classifier: Programming Language :: Python :: 3
Classifier: License :: OSI Approved :: MIT License
Classifier: Operating System :: OS Independent
Requires-Python: >=3.7
Requires-Dist: typing>=3.7.4.3
Requires-Dist: PyGithub>=1.59.0
Requires-Dist: PyYaml>=5.3.0
Requires-Dist: pydantic>=1.10.0
